insane/VERSION.txt
insane/__init__.py
insane/_data.py
insane/_lipid_data.py
insane/cli.py
insane/constants.py
insane/converters.py
insane/core.py
insane/lipids.dat
insane/lipids.py
insane/options.py
insane/pbc.py
insane/structure.py
insane/utils.py
insane/data/diacylester.dat
insane-1.2.0.dist-info/LICENSE
insane-1.2.0.dist-info/METADATA
insane-1.2.0.dist-info/WHEEL
insane-1.2.0.dist-info/entry_points.txt
insane-1.2.0.dist-info/top_level.txt
insane-1.2.0.dist-info/RECORD
